{"main":[{"nu":"AU","idFile":"AU_States","number":"168","states":{"code":"ACT","name":"Australian Capital Territory","nu":"AU-ACT","test":{"into":{"pcr":{"e":"arrival"}}},"link":{"into":"https://safetravel.ica.gov.sg/arriving/overview"}},".9":"1"},{"nu":"AU","idFile":"AU_States","number":"169","states":{"code":"NSW","name":"New South Wales","nu":"AU-NSW","test":{"into":{"pcr":{"e":"arrival"}}},"link":{"into":"https://safetravel.ica.gov.sg/arriving/overview"}},".9":"1"},{"nu":"AU","idFile":"AU_States","number":"170","states":{"code":"NT","name":"Northern Territory","nu":"AU-NT","test":{"into":{"pcr":{"e":"arrival"}}},"link":{"into":"https://safetravel.ica.gov.sg/arriving/overview"}},".9":"1"},{"nu":"AU","idFile":"AU_States","number":"171","states":{"code":"QLD","name":"Queensland","nu":"AU-QLD","test":{"into":{"pcr":{"e":"arrival"}}},"link":{"into":"https://safetravel.ica.gov.sg/arriving/overview"}},".9":"1"},{"nu":"AU","idFile":"AU_States","number":"172","states":{"code":"SA","name":"South Australia","nu":"AU-SA","test":{"into":{"pcr":{"e":"arrival"}}},"link":{"into":"https://safetravel.ica.gov.sg/arriving/overview"}},".9":"1"},{"nu":"AU","idFile":"AU_States","number":"173","states":{"code":"TAS","name":"Tasmania","nu":"AU-TAS","test":{"into":{"pcr":{"e":"arrival"}}},"link":{"into":"https://safetravel.ica.gov.sg/arriving/overview"}},".9":"1"},{"nu":"AU","idFile":"AU_States","number":"174","states":{"code":"VIC","name":"Victoria","nu":"AU-VIC","forbidden":{"into":{"bool":{"e":"1"}}}}},{"nu":"AU","idFile":"AU_States","number":"175","states":{"code":"WA","name":"Western Australia","nu":"AU-WA","test":{"into":{"pcr":{"e":"arrival"}}},"link":{"into":"https://safetravel.ica.gov.sg/arriving/overview"}},".9":"1"},{"nu":"CN","idFile":"CN_States","number":"524","states":{"code":"45","name":"Guangxi","test":{"into":{"pcr":{"e":"arrival"}}},"link":{"into":"https://safetravel.ica.gov.sg/arriving/overview"}}},{"nu":"CN","idFile":"CN_States","number":"525","states":{"code":"15","name":"Nei Mongol","test":{"into":{"pcr":{"e":"arrival"}}},"link":{"into":"https://safetravel.ica.gov.sg/arriving/overview"}}},{"nu":"CN","idFile":"CN_States","number":"526","states":{"code":"64","name":"Ningxia","test":{"into":{"pcr":{"e":"arrival"}}},"link":{"into":"https://safetravel.ica.gov.sg/arriving/overview"}}},{"nu":"CN","idFile":"CN_States","number":"527","states":{"code":"65","name":"Xinjiang","test":{"into":{"pcr":{"e":"arrival"}}},"link":{"into":"https://safetravel.ica.gov.sg/arriving/overview"}}},{"nu":"CN","idFile":"CN_States","number":"528","states":{"code":"54","name":"Xizang","test":{"into":{"pcr":{"e":"arrival"}}},"link":{"into":"https://safetravel.ica.gov.sg/arriving/overview"}}},{"nu":"CN","idFile":"CN_States","number":"529","states":{"code":"11","name":"Beijing","test":{"into":{"pcr":{"e":"arrival"}}},"link":{"into":"https://safetravel.ica.gov.sg/arriving/overview"}}},{"nu":"CN","idFile":"CN_States","number":"530","states":{"code":"50","name":"Chongqing","nu":"CHL","test":{"into":{"pcr":{"e":"arrival"}}},"link":{"into":"https://safetravel.ica.gov.sg/arriving/overview"}}},{"nu":"CN","idFile":"CN_States","number":"531","states":{"code":"31","name":"Shanghai","test":{"into":{"pcr":{"e":"arrival"}}},"link":{"into":"https://safetravel.ica.gov.sg/arriving/overview"}}},{"nu":"CN","idFile":"CN_States","number":"532","states":{"code":"12","name":"Tianjin","test":{"into":{"pcr":{"e":"arrival"}}},"link":{"into":"https://safetravel.ica.gov.sg/arriving/overview"}}},{"nu":"CN","idFile":"CN_States","number":"533","states":{"code":"34","name":"Anhui","test":{"into":{"pcr":{"e":"arrival"}}},"link":{"into":"https://safetravel.ica.gov.sg/arriving/overview"}}},{"nu":"CN","idFile":"CN_States","number":"534","states":{"code":"35","name":"Fujian","test":{"into":{"pcr":{"e":"arrival"}}},"link":{"into":"https://safetravel.ica.gov.sg/arriving/overview"}}},{"nu":"CN","idFile":"CN_States","number":"535","states":{"code":"62","name":"Gansu","test":{"into":{"pcr":{"e":"arrival"}}},"link":{"into":"https://safetravel.ica.gov.sg/arriving/overview"}}},{"nu":"CN","idFile":"CN_States","number":"536","states":{"code":"44","name":"Guangdong","test":{"into":{"pcr":{"e":"arrival"}}},"link":{"into":"https://safetravel.ica.gov.sg/arriving/overview"}}},{"nu":"CN","idFile":"CN_States","number":"537","states":{"code":"52","name":"Guizhou","test":{"into":{"pcr":{"e":"arrival"}}},"link":{"into":"https://safetravel.ica.gov.sg/arriving/overview"}}},{"nu":"CN","idFile":"CN_States","number":"538","states":{"code":"46","name":"Hainan","test":{"into":{"pcr":{"e":"arrival"}}},"link":{"into":"https://safetravel.ica.gov.sg/arriving/overview"}}},{"nu":"CN","idFile":"CN_States","number":"539","states":{"code":"13","name":"Hebei","test":{"into":{"pcr":{"e":"arrival"}}},"link":{"into":"https://safetravel.ica.gov.sg/arriving/overview"}}},{"nu":"CN","idFile":"CN_States","number":"540","states":{"code":"23","name":"Heilongjiang","test":{"into":{"pcr":{"e":"arrival"}}},"link":{"into":"https://safetravel.ica.gov.sg/arriving/overview"}}},{"nu":"CN","idFile":"CN_States","number":"541","states":{"code":"41","name":"Henan","test":{"into":{"pcr":{"e":"arrival"}}},"link":{"into":"https://safetravel.ica.gov.sg/arriving/overview"}}},{"nu":"CN","idFile":"CN_States","number":"542","states":{"code":"42","name":"Hubei","test":{"into":{"pcr":{"e":"arrival"}}},"link":{"into":"https://safetravel.ica.gov.sg/arriving/overview"}}},{"nu":"CN","idFile":"CN_States","number":"543","states":{"code":"43","name":"Hunan","test":{"into":{"pcr":{"e":"arrival"}}},"link":{"into":"https://safetravel.ica.gov.sg/arriving/overview"}}},{"nu":"CN","idFile":"CN_States","number":"544","states":{"code":"32","name":"Jiangsu","test":{"into":{"pcr":{"e":"arrival"}}},"link":{"into":"https://safetravel.ica.gov.sg/arriving/overview"}}},{"nu":"CN","idFile":"CN_States","number":"545","states":{"code":"36","name":"Jiangxi","nu":"CHN","test":{"into":{"pcr":{"e":"arrival"}}},"link":{"into":"https://safetravel.ica.gov.sg/arriving/overview"}}},{"nu":"CN","idFile":"CN_States","number":"546","states":{"code":"22","name":"Jilin","test":{"into":{"pcr":{"e":"arrival"}}},"link":{"into":"https://safetravel.ica.gov.sg/arriving/overview"}}},{"nu":"CN","idFile":"CN_States","number":"547","states":{"code":"21","name":"Liaoning","test":{"into":{"pcr":{"e":"arrival"}}},"link":{"into":"https://safetravel.ica.gov.sg/arriving/overview"}}},{"nu":"CN","idFile":"CN_States","number":"548","states":{"code":"63","name":"Qinghai","test":{"into":{"pcr":{"e":"arrival"}}},"link":{"into":"https://safetravel.ica.gov.sg/arriving/overview"}}},{"nu":"CN","idFile":"CN_States","number":"549","states":{"code":"61","name":"Shaanxi","test":{"into":{"pcr":{"e":"arrival"}}},"link":{"into":"https://safetravel.ica.gov.sg/arriving/overview"}}},{"nu":"CN","idFile":"CN_States","number":"550","states":{"code":"37","name":"Shandong","test":{"into":{"pcr":{"e":"arrival"}}},"link":{"into":"https://safetravel.ica.gov.sg/arriving/overview"}}},{"nu":"CN","idFile":"CN_States","number":"551","states":{"code":"14","name":"Shanxi","test":{"into":{"pcr":{"e":"arrival"}}},"link":{"into":"https://safetravel.ica.gov.sg/arriving/overview"}}},{"nu":"CN","idFile":"CN_States","number":"552","states":{"code":"51","name":"Sichuan","test":{"into":{"pcr":{"e":"arrival"}}},"link":{"into":"https://safetravel.ica.gov.sg/arriving/overview"}}},{"nu":"CN","idFile":"CN_States","number":"553","states":{"code":"71","name":"Taiwan","test":{"into":{"pcr":{"e":"arrival"}}},"link":{"into":"https://safetravel.ica.gov.sg/arriving/overview"}}},{"nu":"CN","idFile":"CN_States","number":"554","states":{"code":"53","name":"Yunnan","test":{"into":{"pcr":{"e":"arrival"}}},"link":{"into":"https://safetravel.ica.gov.sg/arriving/overview"}}},{"nu":"CN","idFile":"CN_States","number":"555","states":{"code":"33","name":"Zhejiang","test":{"into":{"pcr":{"e":"arrival"}}},"link":{"into":"https://safetravel.ica.gov.sg/arriving/overview"}}},{"nu":"CN","idFile":"CN_States","number":"556","states":{"code":"91","name":"Hong Kong","test":{"into":{"pcr":{"e":"arrival"}}},"link":{"into":"https://safetravel.ica.gov.sg/arriving/overview"}}},{"nu":"CN","idFile":"CN_States","number":"557","states":{"code":"92","name":"Macao","test":{"into":{"pcr":{"e":"arrival"}}},"link":{"into":"https://safetravel.ica.gov.sg/arriving/overview"}}},{"nu":"CN","idFile":"CN_States","number":"558","states":{"name":"Hong Kong Island","test":{"into":{"pcr":{"e":"arrival"}}},"link":{"into":"https://safetravel.ica.gov.sg/arriving/overview"}}},{"nu":"CN","idFile":"CN_States","number":"559","states":{"code":"KOWLOON","name":"Kowloon","test":{"into":{"pcr":{"e":"arrival"}}},"link":{"into":"https://safetravel.ica.gov.sg/arriving/overview"}}},{"nu":"CN","idFile":"CN_States","number":"560","states":{"code":"NEW TERRITORIES","name":"New Territories","test":{"into":{"pcr":{"e":"arrival"}}},"link":{"into":"https://safetravel.ica.gov.sg/arriving/overview"}}}]}
